odoo/addons/l10n_din5008_move_name/README.rst
odoo/addons/l10n_din5008_move_name/__init__.py
odoo/addons/l10n_din5008_move_name/__manifest__.py
odoo/addons/l10n_din5008_move_name/i18n/l10n_din5008_move_name.pot
odoo/addons/l10n_din5008_move_name/models/__init__.py
odoo/addons/l10n_din5008_move_name/models/account_move.py
odoo/addons/l10n_din5008_move_name/readme/CONTRIBUTORS.md
odoo/addons/l10n_din5008_move_name/readme/DESCRIPTION.md
odoo/addons/l10n_din5008_move_name/static/description/icon.png
odoo/addons/l10n_din5008_move_name/static/description/index.html
odoo/addons/l10n_din5008_move_name/tests/__init__.py
odoo/addons/l10n_din5008_move_name/tests/test_din5008.py
odoo_addon_l10n_din5008_move_name-17.0.1.1.0.dist-info/METADATA
odoo_addon_l10n_din5008_move_name-17.0.1.1.0.dist-info/WHEEL
odoo_addon_l10n_din5008_move_name-17.0.1.1.0.dist-info/top_level.txt
odoo_addon_l10n_din5008_move_name-17.0.1.1.0.dist-info/RECORD
