Metadata-Version: 2.1
Name: odoo-addon-l10n_din5008_move_name
Version: 17.0.1.1.0
Requires-Python: >=3.10
Requires-Dist: odoo>=17.0a,<17.1dev
Summary: Add Account move name on the name of the move
Home-page: https://github.com/OCA/l10n-germany
License: AGPL-3
Author: Dixmit,Odoo Community Association (OCA)
Author-email: support@odoo-community.org
Classifier: Programming Language :: Python
Classifier: Framework :: Odoo
Classifier: Framework :: Odoo :: 17.0
Classifier: License :: OSI Approved :: GNU Affero General Public License v3
